{
    "product": {
        "card":{
                "cardTitle": "Informationen zur Aktualisierung des Produktpreises"
        },
        "date": {
            "validFrom": "Gültig ab",
            "endFrom": "Gültig bis"
        },
        "price": {
            "gross": "Neupreis (brutto)",
            "net": "Neupreis (netto)"
        },
        "switch": {
            "week" : "Für jedes Wochenende"
        },
        "productWeekHelpText": {
            "label": "Product numbers help you identify and manage your products. To achieve this, try and keep a consistent structure in your product numbers. You can define product number templates in {link}.",
            "linkText": "settings"
        },
        "updateprice": {
            "cardTitle" :"Produktpreis aktualisieren",
            "grossPrice": "Bruttopreis",
            "netPrice": "Nettopreis",
            "startDate": "Gültig ab",
            "endDate": "Gültig bis",
            "status" : "Status",
            "priceDelete": "löschen",
            "successTitle": "Erfolg",
            "successMessage": "Erfolgreich gelöscht"
        }
    }
}
